MANIFEST.in
setup.py
LocExtract/LocExtract.py
LocExtract/__init__.py
LocExtract.egg-info/PKG-INFO
LocExtract.egg-info/SOURCES.txt
LocExtract.egg-info/dependency_links.txt
LocExtract.egg-info/top_level.txt
LocExtract/resource/A.pkl
LocExtract/resource/A_re.pkl
LocExtract/resource/C.pkl
LocExtract/resource/CA.pkl
LocExtract/resource/CA_re.pkl
LocExtract/resource/C_re.pkl
LocExtract/resource/P.pkl
LocExtract/resource/PA.pkl
LocExtract/resource/PA_re.pkl
LocExtract/resource/PC.pkl
LocExtract/resource/PCA.pkl
LocExtract/resource/PCA_re.pkl
LocExtract/resource/PC_re.pkl
LocExtract/resource/P_re.pkl