Metadata-Version: 1.0
Name: LocExtract
Version: 1.0.2
Summary: An china location extraction algorithm
Home-page: UNKNOWN
Author: lh
Author-email: huihuil@bupt.edu.cn
License: MIT Licence
Keywords: pip,LocExtract,LocationExtract
Platform: any
